loudly_py_sdk/__init__.py
loudly_py_sdk/client.py
loudly_py_sdk/exceptions.py
loudly_py_sdk-0.1.0.dist-info/METADATA
loudly_py_sdk-0.1.0.dist-info/WHEEL
loudly_py_sdk-0.1.0.dist-info/top_level.txt
loudly_py_sdk-0.1.0.dist-info/RECORD
