Metadata-Version: 2.4
Name: loudly-py-sdk
Version: 0.1.0
Summary: Python SDK for Loudly Music API
License: MIT
Requires-Python: >=3.8
Requires-Dist: requests>=2.25.0
Requires-Dist: python-dotenv>=1.0.0
